ontolog/__init__.py
ontolog/util/__init__.py
ontolog/util/generic.py
ontolog-0.0.1.dist-info/LICENSE
ontolog-0.0.1.dist-info/METADATA
ontolog-0.0.1.dist-info/WHEEL
ontolog-0.0.1.dist-info/top_level.txt
ontolog-0.0.1.dist-info/RECORD
